statprocon/__init__.py
statprocon/py.typed
statprocon/charts/__init__.py
statprocon/charts/xmr/__init__.py
statprocon/charts/xmr/base.py
statprocon/charts/xmr/constants.py
statprocon/charts/xmr/exceptions.py
statprocon/charts/xmr/types.py
statprocon/charts/xmr/limits/__init__.py
statprocon/charts/xmr/limits/trending.py
statprocon-1.0.2.dist-info/METADATA
statprocon-1.0.2.dist-info/WHEEL
statprocon-1.0.2.dist-info/licenses/LICENSE
statprocon-1.0.2.dist-info/RECORD
