Metadata-Version: 2.3
Name: statprocon
Version: 1.0.2
Summary: A Python helper library for generating Process Behaviour Charts
Project-URL: Homepage, https://github.com/mattmccormick/statprocon
Project-URL: Bug Tracker, https://github.com/mattmccormick/statprocon/issues
Project-URL: Changelog, https://github.com/mattmccormick/statprocon/blob/main/CHANGELOG.md
Author-email: Matt McCormick <mattmccor@gmail.com>
License-File: LICENSE
Keywords: Process Behavior Chart,Process Behaviour Chart,QCC,Quality Control Chart,SPC,Shewhart,Statistical Process Control,Wheeler,XmR
Classifier: License :: OSI Approved :: MIT License
Classifier: Operating System :: OS Independent
Classifier: Programming Language :: Python :: 3
Requires-Python: >=3.8
Requires-Dist: packaging
Requires-Dist: typing-extensions
